<ti:work xml:lang="lat" xmlns:ti="http://chs.harvard.edu/xmlns/cts" urn="urn:cts:latinLit:stoa0040.stoa080a" groupUrn="urn:cts:latinLit:stoa0040">
  <ti:title xml:lang="eng">Liber de Divinis Scripturis sive Speculum quod fertur S. Augustini</ti:title>
  <ti:edition urn="urn:cts:latinLit:stoa0040.stoa080a.opp-lat1" workUrn="urn:cts:latinLit:stoa0040.stoa080a">
    <ti:label xml:lang="eng">Liber de Divinis Scripturis sive Speculum quod fertur S. Augustini</ti:label>
    <ti:description xml:lang="eng">S. Aurelius Augustinus, Liber de Divinis Scripturis sive Speculum quod fertur S. Augustini</ti:description>
  </ti:edition>
</ti:work>
