<ti:work xml:lang="lat" xmlns:ti="http://chs.harvard.edu/xmlns/cts" groupUrn="urn:cts:latinLit:stoa0292d" urn="urn:cts:latinLit:stoa0292d.stoa001">
  <ti:title xml:lang="lat">Historia persecutionis Africanae provinciae</ti:title>
  <ti:edition workUrn="urn:cts:latinLit:stoa0292d.stoa001" urn="urn:cts:latinLit:stoa0292d.stoa001.opp-lat1">
    <ti:label xml:lang="lat">Historia persecutionis Africanae provinciae</ti:label>
    <ti:description xml:lang="mul">Victor Vitensis. Victoris episcopi Vitensis Historia persecutionis Africanae provinciae
    (Corpus Scriptorum Ecclesiasticorum, Volume 7). Petschenig, Michael, editor. Vienna: Gerold, 1881.</ti:description>
  </ti:edition>
</ti:work>
